konami_mcp_demo/__init__.py
konami_mcp_demo-0.1.0.dist-info/WHEEL
konami_mcp_demo-0.1.0.dist-info/entry_points.txt
konami_mcp_demo-0.1.0.dist-info/METADATA
konami_mcp_demo-0.1.0.dist-info/RECORD
