Metadata-Version: 2.3
Name: konami-mcp-demo
Version: 0.1.0
Summary: Add your description here
Author: konami0328
Author-email: konami0328 <brendaniu10010@gmail.com>
Requires-Dist: mcp[cli]>=1.14.1
Requires-Python: >=3.13
